README.md
setup.py
distributions_for_datascience/Binomialdistribution.py
distributions_for_datascience/Gaussiandistribution.py
distributions_for_datascience/Generaldistribution.py
distributions_for_datascience/__init__.py
distributions_for_datascience.egg-info/PKG-INFO
distributions_for_datascience.egg-info/SOURCES.txt
distributions_for_datascience.egg-info/dependency_links.txt
distributions_for_datascience.egg-info/not-zip-safe
distributions_for_datascience.egg-info/top_level.txt