Metadata-Version: 1.0
Name: distributions-for-datascience
Version: 0.1
Summary: Gaussian / Binomial distributions
Home-page: UNKNOWN
Author: Thomas
Author-email: thomas.grusz@gmail.com
License: UNKNOWN
Platform: UNKNOWN
